reflex_color_pick/__init__.py
reflex_color_pick/color_pick.py
reflex_color_pick/color_pick.pyi
reflex_color_pick-0.0.1.dist-info/METADATA
reflex_color_pick-0.0.1.dist-info/WHEEL
reflex_color_pick-0.0.1.dist-info/top_level.txt
reflex_color_pick-0.0.1.dist-info/RECORD
